{
  "timestamp": "2026-04-02T12:27:25.676685",
  "generated_at_local": "2026-04-02 12:27:25 KST",
  "candle_close_time": "2026-04-02 12:15 KST",
  "exchange": "binance",
  "market_type": "futures",
  "timezone": "Asia/Seoul",
  "symbol_primary": "ETHUSDT",
  "symbol_reference": "BTCUSDT",
  "_format": "compact",
  "_note": "15분봉 완성 시점 자동 생성. candle_close_time이 데이터 기준 시점.",
  "assets": {
    "ETHUSDT": {
      "price": 2072.57,
      "change_24h_pct": -1.15,
      "funding_rate": -0.00013823,
      "timeframes": {
        "15m": {
          "close": 2073.2,
          "rsi": 31.7,
          "volume_change_pct": 362.32,
          "ma50": 2129.43,
          "ema25": 2110.1,
          "bb_position": 0.1773,
          "above_ma50": false,
          "above_ema25": false,
          "flags": {
            "rsi_oversold": false,
            "rsi_overbought": false,
            "rsi_neutral": false,
            "near_upper_band": false,
            "near_lower_band": true,
            "price_above_ma50": false,
            "price_above_ema25": false,
            "volume_surge": true,
            "volume_dry": false
          }
        },
        "30m": {
          "close": 2073.58,
          "rsi": 29.5,
          "volume_change_pct": 138.37,
          "ma50": 2127.64,
          "ema25": 2120.66,
          "bb_position": -0.017,
          "above_ma50": false,
          "above_ema25": false,
          "flags": {
            "rsi_oversold": true,
            "rsi_overbought": false,
            "rsi_neutral": false,
            "near_upper_band": false,
            "near_lower_band": true,
            "price_above_ma50": false,
            "price_above_ema25": false,
            "volume_surge": true,
            "volume_dry": false
          }
        },
        "1h": {
          "close": 2073.59,
          "rsi": 37.4,
          "volume_change_pct": 9.66,
          "ma50": 2099.66,
          "ema25": 2117.22,
          "bb_position": -0.1112,
          "above_ma50": false,
          "above_ema25": false,
          "flags": {
            "rsi_oversold": false,
            "rsi_overbought": false,
            "rsi_neutral": false,
            "near_upper_band": false,
            "near_lower_band": true,
            "price_above_ma50": false,
            "price_above_ema25": false,
            "volume_surge": false,
            "volume_dry": false
          }
        },
        "4h": {
          "close": 2073.22,
          "rsi": 48.8,
          "volume_change_pct": 12.64,
          "ma50": 2066.78,
          "ema25": 2080.32,
          "bb_position": 0.4798,
          "above_ma50": true,
          "above_ema25": false,
          "flags": {
            "rsi_oversold": false,
            "rsi_overbought": false,
            "rsi_neutral": true,
            "near_upper_band": false,
            "near_lower_band": false,
            "price_above_ma50": true,
            "price_above_ema25": false,
            "volume_surge": false,
            "volume_dry": false
          }
        },
        "1d": {
          "close": 2073.23,
          "rsi": 48.8,
          "volume_change_pct": -18.81,
          "ma50": 2043.81,
          "ema25": 2087.3,
          "bb_position": 0.3795,
          "above_ma50": true,
          "above_ema25": false,
          "flags": {
            "rsi_oversold": false,
            "rsi_overbought": false,
            "rsi_neutral": true,
            "near_upper_band": false,
            "near_lower_band": false,
            "price_above_ma50": true,
            "price_above_ema25": false,
            "volume_surge": false,
            "volume_dry": false
          }
        },
        "2d": {
          "close": 2073.2,
          "rsi": 46.0,
          "volume_change_pct": -17.4,
          "ma50": 2430.45,
          "ema25": 2150.25,
          "bb_position": 0.5405,
          "above_ma50": false,
          "above_ema25": false,
          "flags": {
            "rsi_oversold": false,
            "rsi_overbought": false,
            "rsi_neutral": true,
            "near_upper_band": false,
            "near_lower_band": false,
            "price_above_ma50": false,
            "price_above_ema25": false,
            "volume_surge": false,
            "volume_dry": false
          }
        }
      },
      "open_interest": {
        "current_usd": 4723839216.0,
        "change_pct_1h": -3.87,
        "change_pct_24h": -1.65,
        "momentum_state": "decelerating",
        "acceleration": -2.61
      },
      "cvd": {
        "futures": {
          "million": -0.22,
          "sma": 1.14,
          "above_sma": false,
          "buy_pct": 48.93,
          "sell_pct": 51.07
        },
        "spot": {
          "cvd_pct": -2.55,
          "buy_pct": 48.7,
          "sell_pct": 51.3
        },
        "divergence": -0.41,
        "divergence_confidence": "low"
      },
      "liquidation": {
        "symbol": "ETH",
        "1h_long_usd": 7901418.0,
        "1h_short_usd": 66872.0,
        "4h_long_usd": 35744407.0,
        "4h_short_usd": 4019233.0,
        "12h_long_usd": 41248546.0,
        "12h_short_usd": 21023243.0,
        "24h_long_usd": 49628824.0,
        "24h_short_usd": 45441658.0,
        "status": "success",
        "total_liquidation_12h": 62271789.0,
        "long_ratio": 66.24,
        "short_ratio": 33.76,
        "_liquidation_note": "12h/24h_long_usd=해당 기간 롱 포지션 강제청산 금액(USD). short_usd=숏 청산 금액. 롱 청산이 많으면 하락 중 롱이 밀린것, 숏 청산이 많으면 상승 중 숏이 밀린것. long_ratio/short_ratio=전체 청산 중 비중(%)",
        "timestamp": 1775100311,
        "source": "coinglass",
        "data_interval": "12h"
      },
      "relative_strength_vs_btc": {
        "1h": 0.65,
        "4h": -0.72,
        "1d": 1.31,
        "1w": -0.93
      },
      "whale_reference": {
        "status": "success",
        "vwap": 2093.91,
        "distance_pct": -0.99,
        "usable": true,
        "cache_reason": null
      },
      "support_resistance": {
        "supports": [
          1913.34,
          1990.18,
          2025.86,
          2063.56
        ],
        "resistances": [
          2103.03,
          2141.59,
          2169.42,
          2204.8
        ]
      },
      "orderbook": {
        "buy_nearest": 2071.8,
        "sell_nearest": 2074.35,
        "top_buy": [
          2067.99,
          2068.09,
          2068.24
        ],
        "top_sell": [],
        "imbalance_ratio": 1.689
      },
      "warnings": []
    },
    "BTCUSDT": {
      "price": 66835.3,
      "change_24h_pct": -1.59,
      "funding_rate": -2.604e-05,
      "timeframes": {
        "15m": {
          "close": 66841.6,
          "rsi": 32.7,
          "volume_change_pct": 417.75,
          "ma50": 68073.2,
          "ema25": 67568.08,
          "bb_position": 0.1981,
          "above_ma50": false,
          "above_ema25": false,
          "flags": {
            "rsi_oversold": false,
            "rsi_overbought": false,
            "rsi_neutral": false,
            "near_upper_band": false,
            "near_lower_band": true,
            "price_above_ma50": false,
            "price_above_ema25": false,
            "volume_surge": true,
            "volume_dry": false
          }
        },
        "30m": {
          "close": 66833.8,
          "rsi": 29.3,
          "volume_change_pct": 116.69,
          "ma50": 68271.12,
          "ema25": 67882.4,
          "bb_position": -0.0048,
          "above_ma50": false,
          "above_ema25": false,
          "flags": {
            "rsi_oversold": true,
            "rsi_overbought": false,
            "rsi_neutral": false,
            "near_upper_band": false,
            "near_lower_band": true,
            "price_above_ma50": false,
            "price_above_ema25": false,
            "volume_surge": true,
            "volume_dry": false
          }
        },
        "1h": {
          "close": 66841.6,
          "rsi": 35.5,
          "volume_change_pct": -4.36,
          "ma50": 67841.47,
          "ema25": 67961.9,
          "bb_position": -0.081,
          "above_ma50": false,
          "above_ema25": false,
          "flags": {
            "rsi_oversold": false,
            "rsi_overbought": false,
            "rsi_neutral": false,
            "near_upper_band": false,
            "near_lower_band": true,
            "price_above_ma50": false,
            "price_above_ema25": false,
            "volume_surge": false,
            "volume_dry": false
          }
        },
        "4h": {
          "close": 66830.1,
          "rsi": 42.9,
          "volume_change_pct": 1.06,
          "ma50": 67978.46,
          "ema25": 67689.66,
          "bb_position": 0.2747,
          "above_ma50": false,
          "above_ema25": false,
          "flags": {
            "rsi_oversold": false,
            "rsi_overbought": false,
            "rsi_neutral": true,
            "near_upper_band": false,
            "near_lower_band": false,
            "price_above_ma50": false,
            "price_above_ema25": false,
            "volume_surge": false,
            "volume_dry": false
          }
        },
        "1d": {
          "close": 66841.6,
          "rsi": 43.5,
          "volume_change_pct": -12.54,
          "ma50": 68643.93,
          "ema25": 68846.08,
          "bb_position": 0.2363,
          "above_ma50": false,
          "above_ema25": false,
          "flags": {
            "rsi_oversold": false,
            "rsi_overbought": false,
            "rsi_neutral": true,
            "near_upper_band": false,
            "near_lower_band": false,
            "price_above_ma50": false,
            "price_above_ema25": false,
            "volume_surge": false,
            "volume_dry": false
          }
        },
        "2d": {
          "close": 66841.6,
          "rsi": 42.2,
          "volume_change_pct": -24.18,
          "ma50": 76991.97,
          "ema25": 70651.55,
          "bb_position": 0.3108,
          "above_ma50": false,
          "above_ema25": false,
          "flags": {
            "rsi_oversold": false,
            "rsi_overbought": false,
            "rsi_neutral": true,
            "near_upper_band": false,
            "near_lower_band": false,
            "price_above_ma50": false,
            "price_above_ema25": false,
            "volume_surge": false,
            "volume_dry": false
          }
        }
      },
      "open_interest": {
        "current_usd": 5902169438.0,
        "change_pct_1h": -0.82,
        "change_pct_24h": -3.91,
        "momentum_state": "accelerating",
        "acceleration": 1.72
      },
      "cvd": {
        "futures": {
          "million": 0.46,
          "sma": 0.63,
          "above_sma": false,
          "buy_pct": 53.26,
          "sell_pct": 46.74
        },
        "spot": {
          "cvd_pct": 10.15,
          "buy_pct": 55.1,
          "sell_pct": 44.9
        },
        "divergence": 3.62,
        "divergence_confidence": "low"
      },
      "liquidation": {
        "symbol": "BTC",
        "1h_long_usd": 2864355.0,
        "1h_short_usd": 73076.0,
        "4h_long_usd": 39287982.0,
        "4h_short_usd": 2342097.0,
        "12h_long_usd": 45857315.0,
        "12h_short_usd": 11215642.0,
        "24h_long_usd": 54445318.0,
        "24h_short_usd": 41583514.0,
        "status": "success",
        "total_liquidation_12h": 57072957.0,
        "long_ratio": 80.35,
        "short_ratio": 19.65,
        "_liquidation_note": "12h/24h_long_usd=해당 기간 롱 포지션 강제청산 금액(USD). short_usd=숏 청산 금액. 롱 청산이 많으면 하락 중 롱이 밀린것, 숏 청산이 많으면 상승 중 숏이 밀린것. long_ratio/short_ratio=전체 청산 중 비중(%)",
        "timestamp": 1775100299,
        "source": "coinglass",
        "data_interval": "12h"
      },
      "relative_strength_vs_btc": null,
      "whale_reference": {
        "status": "success",
        "vwap": 68009.7,
        "distance_pct": -1.72,
        "usable": true,
        "cache_reason": null
      },
      "support_resistance": {
        "supports": [
          59800.0,
          62401.7,
          65692.92,
          66658.27
        ],
        "resistances": [
          67530.01,
          69003.08,
          70732.96,
          71999.9
        ]
      },
      "orderbook": {
        "buy_nearest": 66792.82,
        "sell_nearest": 66851.44,
        "top_buy": [],
        "top_sell": [],
        "imbalance_ratio": 1.257
      },
      "warnings": []
    }
  }
}