{
  "timestamp": "2026-04-02T10:07:25.548124",
  "generated_at_local": "2026-04-02 10:07:25 KST",
  "candle_close_time": "2026-04-02 10:00 KST",
  "exchange": "binance",
  "market_type": "futures",
  "timezone": "Asia/Seoul",
  "symbol_primary": "ETHUSDT",
  "symbol_reference": "BTCUSDT",
  "_format": "compact",
  "_note": "15분봉 완성 시점 자동 생성. candle_close_time이 데이터 기준 시점.",
  "assets": {
    "ETHUSDT": {
      "price": 2123.08,
      "change_24h_pct": 0.82,
      "funding_rate": -0.00011181,
      "timeframes": {
        "15m": {
          "close": 2124.41,
          "rsi": 39.3,
          "volume_change_pct": 9.19,
          "ma50": 2136.64,
          "ema25": 2141.03,
          "bb_position": -0.0788,
          "above_ma50": false,
          "above_ema25": false,
          "flags": {
            "rsi_oversold": false,
            "rsi_overbought": false,
            "rsi_neutral": false,
            "near_upper_band": false,
            "near_lower_band": true,
            "price_above_ma50": false,
            "price_above_ema25": false,
            "volume_surge": false,
            "volume_dry": false
          }
        },
        "30m": {
          "close": 2126.77,
          "rsi": 45.2,
          "volume_change_pct": -25.42,
          "ma50": 2129.22,
          "ema25": 2136.94,
          "bb_position": 0.1213,
          "above_ma50": false,
          "above_ema25": false,
          "flags": {
            "rsi_oversold": false,
            "rsi_overbought": false,
            "rsi_neutral": true,
            "near_upper_band": false,
            "near_lower_band": true,
            "price_above_ma50": false,
            "price_above_ema25": false,
            "volume_surge": false,
            "volume_dry": false
          }
        },
        "1h": {
          "close": 2124.41,
          "rsi": 49.8,
          "volume_change_pct": -28.11,
          "ma50": 2099.4,
          "ema25": 2126.85,
          "bb_position": 0.1882,
          "above_ma50": true,
          "above_ema25": false,
          "flags": {
            "rsi_oversold": false,
            "rsi_overbought": false,
            "rsi_neutral": true,
            "near_upper_band": false,
            "near_lower_band": true,
            "price_above_ma50": true,
            "price_above_ema25": false,
            "volume_surge": false,
            "volume_dry": false
          }
        },
        "4h": {
          "close": 2124.41,
          "rsi": 61.3,
          "volume_change_pct": -2.34,
          "ma50": 2067.81,
          "ema25": 2084.26,
          "bb_position": 0.7453,
          "above_ma50": true,
          "above_ema25": true,
          "flags": {
            "rsi_oversold": false,
            "rsi_overbought": false,
            "rsi_neutral": false,
            "near_upper_band": false,
            "near_lower_band": false,
            "price_above_ma50": true,
            "price_above_ema25": true,
            "volume_surge": false,
            "volume_dry": false
          }
        },
        "1d": {
          "close": 2125.66,
          "rsi": 52.6,
          "volume_change_pct": -21.39,
          "ma50": 2044.86,
          "ema25": 2091.33,
          "bb_position": 0.5072,
          "above_ma50": true,
          "above_ema25": true,
          "flags": {
            "rsi_oversold": false,
            "rsi_overbought": false,
            "rsi_neutral": true,
            "near_upper_band": false,
            "near_lower_band": false,
            "price_above_ma50": true,
            "price_above_ema25": true,
            "volume_surge": false,
            "volume_dry": false
          }
        },
        "2d": {
          "close": 2124.41,
          "rsi": 48.0,
          "volume_change_pct": -18.58,
          "ma50": 2431.48,
          "ema25": 2154.19,
          "bb_position": 0.6539,
          "above_ma50": false,
          "above_ema25": false,
          "flags": {
            "rsi_oversold": false,
            "rsi_overbought": false,
            "rsi_neutral": true,
            "near_upper_band": false,
            "near_lower_band": false,
            "price_above_ma50": false,
            "price_above_ema25": false,
            "volume_surge": false,
            "volume_dry": false
          }
        }
      },
      "open_interest": {
        "current_usd": 4976535984.0,
        "change_pct_1h": 1.48,
        "change_pct_24h": 4.59,
        "momentum_state": "accelerating",
        "acceleration": 1.59
      },
      "cvd": {
        "futures": {
          "million": -0.97,
          "sma": -0.64,
          "above_sma": false,
          "buy_pct": 44.72,
          "sell_pct": 55.28
        },
        "spot": {
          "cvd_pct": 3.52,
          "buy_pct": 51.8,
          "sell_pct": 48.2
        },
        "divergence": 14.08,
        "divergence_confidence": "low"
      },
      "liquidation": {
        "symbol": "ETH",
        "1h_long_usd": 4399948.0,
        "1h_short_usd": 1493768.0,
        "4h_long_usd": 6747074.0,
        "4h_short_usd": 5066139.0,
        "12h_long_usd": 13449521.0,
        "12h_short_usd": 21339599.0,
        "24h_long_usd": 22286143.0,
        "24h_short_usd": 44710679.0,
        "status": "success",
        "total_liquidation_12h": 34789120.0,
        "long_ratio": 38.66,
        "short_ratio": 61.34,
        "_liquidation_note": "12h/24h_long_usd=해당 기간 롱 포지션 강제청산 금액(USD). short_usd=숏 청산 금액. 롱 청산이 많으면 하락 중 롱이 밀린것, 숏 청산이 많으면 상승 중 숏이 밀린것. long_ratio/short_ratio=전체 청산 중 비중(%)",
        "timestamp": 1775091950,
        "source": "coinglass",
        "data_interval": "12h"
      },
      "relative_strength_vs_btc": {
        "1h": 0.3,
        "4h": -36.44,
        "1d": 1.31,
        "1w": -0.86
      },
      "whale_reference": {
        "status": "success",
        "vwap": 2088.3,
        "distance_pct": 1.69,
        "usable": true,
        "cache_reason": null
      },
      "support_resistance": {
        "supports": [
          1990.18,
          2019.61,
          2079.06,
          2112.04
        ],
        "resistances": [
          2141.72,
          2169.95,
          2204.8,
          2272.7
        ]
      },
      "orderbook": {
        "buy_nearest": 2130.67,
        "sell_nearest": 2133.35,
        "top_buy": [
          2128.38,
          2130.45
        ],
        "top_sell": [
          2136.47,
          2136.43,
          2134.93
        ],
        "imbalance_ratio": 0.667
      },
      "warnings": []
    },
    "BTCUSDT": {
      "price": 67730.4,
      "change_24h_pct": -0.73,
      "funding_rate": 2.878e-05,
      "timeframes": {
        "15m": {
          "close": 67730.1,
          "rsi": 37.1,
          "volume_change_pct": 56.49,
          "ma50": 68313.1,
          "ema25": 68214.85,
          "bb_position": -0.1443,
          "above_ma50": false,
          "above_ema25": false,
          "flags": {
            "rsi_oversold": false,
            "rsi_overbought": false,
            "rsi_neutral": false,
            "near_upper_band": false,
            "near_lower_band": true,
            "price_above_ma50": false,
            "price_above_ema25": false,
            "volume_surge": true,
            "volume_dry": false
          }
        },
        "30m": {
          "close": 67730.1,
          "rsi": 39.7,
          "volume_change_pct": -40.63,
          "ma50": 68351.12,
          "ema25": 68251.09,
          "bb_position": 0.0438,
          "above_ma50": false,
          "above_ema25": false,
          "flags": {
            "rsi_oversold": false,
            "rsi_overbought": false,
            "rsi_neutral": false,
            "near_upper_band": false,
            "near_lower_band": true,
            "price_above_ma50": false,
            "price_above_ema25": false,
            "volume_surge": false,
            "volume_dry": true
          }
        },
        "1h": {
          "close": 67751.1,
          "rsi": 44.1,
          "volume_change_pct": -41.9,
          "ma50": 67878.27,
          "ema25": 68191.5,
          "bb_position": 0.0035,
          "above_ma50": false,
          "above_ema25": false,
          "flags": {
            "rsi_oversold": false,
            "rsi_overbought": false,
            "rsi_neutral": true,
            "near_upper_band": false,
            "near_lower_band": true,
            "price_above_ma50": false,
            "price_above_ema25": false,
            "volume_surge": false,
            "volume_dry": true
          }
        },
        "4h": {
          "close": 67751.1,
          "rsi": 49.9,
          "volume_change_pct": -10.12,
          "ma50": 67996.88,
          "ema25": 67760.51,
          "bb_position": 0.5488,
          "above_ma50": false,
          "above_ema25": false,
          "flags": {
            "rsi_oversold": false,
            "rsi_overbought": false,
            "rsi_neutral": true,
            "near_upper_band": false,
            "near_lower_band": false,
            "price_above_ma50": false,
            "price_above_ema25": false,
            "volume_surge": false,
            "volume_dry": false
          }
        },
        "1d": {
          "close": 67751.1,
          "rsi": 45.9,
          "volume_change_pct": -14.61,
          "ma50": 68662.12,
          "ema25": 68916.04,
          "bb_position": 0.3173,
          "above_ma50": false,
          "above_ema25": false,
          "flags": {
            "rsi_oversold": false,
            "rsi_overbought": false,
            "rsi_neutral": true,
            "near_upper_band": false,
            "near_lower_band": false,
            "price_above_ma50": false,
            "price_above_ema25": false,
            "volume_surge": false,
            "volume_dry": false
          }
        },
        "2d": {
          "close": 67768.2,
          "rsi": 43.6,
          "volume_change_pct": -25.02,
          "ma50": 77010.51,
          "ema25": 70722.83,
          "bb_position": 0.3969,
          "above_ma50": false,
          "above_ema25": false,
          "flags": {
            "rsi_oversold": false,
            "rsi_overbought": false,
            "rsi_neutral": true,
            "near_upper_band": false,
            "near_lower_band": false,
            "price_above_ma50": false,
            "price_above_ema25": false,
            "volume_surge": false,
            "volume_dry": false
          }
        }
      },
      "open_interest": {
        "current_usd": 6106372200.0,
        "change_pct_1h": 0.57,
        "change_pct_24h": 0.12,
        "momentum_state": "accelerating",
        "acceleration": 0.73
      },
      "cvd": {
        "futures": {
          "million": 1.13,
          "sma": -0.62,
          "above_sma": true,
          "buy_pct": 57.91,
          "sell_pct": 42.09
        },
        "spot": {
          "cvd_pct": -3.54,
          "buy_pct": 48.2,
          "sell_pct": 51.8
        },
        "divergence": -19.35,
        "divergence_confidence": "low"
      },
      "liquidation": {
        "symbol": "BTC",
        "1h_long_usd": 6115643.0,
        "1h_short_usd": 984829.0,
        "4h_long_usd": 7339196.0,
        "4h_short_usd": 1628900.0,
        "12h_long_usd": 10956533.0,
        "12h_short_usd": 12549842.0,
        "24h_long_usd": 18489139.0,
        "24h_short_usd": 40657603.0,
        "status": "success",
        "total_liquidation_12h": 23506375.0,
        "long_ratio": 46.61,
        "short_ratio": 53.39,
        "_liquidation_note": "12h/24h_long_usd=해당 기간 롱 포지션 강제청산 금액(USD). short_usd=숏 청산 금액. 롱 청산이 많으면 하락 중 롱이 밀린것, 숏 청산이 많으면 상승 중 숏이 밀린것. long_ratio/short_ratio=전체 청산 중 비중(%)",
        "timestamp": 1775091938,
        "source": "coinglass",
        "data_interval": "12h"
      },
      "relative_strength_vs_btc": null,
      "whale_reference": {
        "status": "success",
        "vwap": 68009.7,
        "distance_pct": -0.45,
        "usable": true,
        "cache_reason": null
      },
      "support_resistance": {
        "supports": [
          55846.84,
          59800.0,
          65933.89,
          67482.86
        ],
        "resistances": [
          67889.13,
          68948.26,
          70732.96,
          71999.9
        ]
      },
      "orderbook": {
        "buy_nearest": 67929.65,
        "sell_nearest": 68004.21,
        "top_buy": [
          67898.5
        ],
        "top_sell": [],
        "imbalance_ratio": 1.122
      },
      "warnings": [
        "volume_contracting"
      ]
    }
  }
}