{
  "timestamp": "2026-04-02T22:02:36.587570",
  "generated_at_local": "2026-04-02 22:02:36 KST",
  "candle_close_time": "2026-04-02 22:00 KST",
  "exchange": "binance",
  "market_type": "futures",
  "timezone": "Asia/Seoul",
  "symbol_primary": "SOLUSDT",
  "symbol_reference": "BTCUSDT",
  "_format": "compact",
  "_note": "15분봉 완성 시점 자동 생성. candle_close_time이 데이터 기준 시점.",
  "assets": {
    "SOLUSDT": {
      "price": 77.87,
      "change_24h_pct": -6.11,
      "funding_rate": -0.00014165,
      "timeframes": {
        "15m": {
          "close": 77.91,
          "rsi": 27.7,
          "volume_change_pct": 51.92,
          "ma50": 79.05,
          "ema25": 78.76,
          "bb_position": -0.003,
          "above_ma50": false,
          "above_ema25": false,
          "flags": {
            "rsi_oversold": true,
            "rsi_overbought": false,
            "rsi_neutral": false,
            "near_upper_band": false,
            "near_lower_band": true,
            "price_above_ma50": false,
            "price_above_ema25": false,
            "volume_surge": true,
            "volume_dry": false
          }
        },
        "30m": {
          "close": 77.91,
          "rsi": 28.4,
          "volume_change_pct": -17.39,
          "ma50": 81.03,
          "ema25": 79.37,
          "bb_position": -0.1177,
          "above_ma50": false,
          "above_ema25": false,
          "flags": {
            "rsi_oversold": true,
            "rsi_overbought": false,
            "rsi_neutral": false,
            "near_upper_band": false,
            "near_lower_band": true,
            "price_above_ma50": false,
            "price_above_ema25": false,
            "volume_surge": false,
            "volume_dry": false
          }
        },
        "1h": {
          "close": 77.91,
          "rsi": 29.7,
          "volume_change_pct": -53.81,
          "ma50": 81.86,
          "ema25": 80.36,
          "bb_position": 0.1941,
          "above_ma50": false,
          "above_ema25": false,
          "flags": {
            "rsi_oversold": true,
            "rsi_overbought": false,
            "rsi_neutral": false,
            "near_upper_band": false,
            "near_lower_band": true,
            "price_above_ma50": false,
            "price_above_ema25": false,
            "volume_surge": false,
            "volume_dry": true
          }
        },
        "4h": {
          "close": 77.91,
          "rsi": 32.0,
          "volume_change_pct": -0.9,
          "ma50": 83.97,
          "ema25": 81.97,
          "bb_position": -0.0108,
          "above_ma50": false,
          "above_ema25": false,
          "flags": {
            "rsi_oversold": false,
            "rsi_overbought": false,
            "rsi_neutral": false,
            "near_upper_band": false,
            "near_lower_band": true,
            "price_above_ma50": false,
            "price_above_ema25": false,
            "volume_surge": false,
            "volume_dry": false
          }
        },
        "1d": {
          "close": 77.92,
          "rsi": 35.8,
          "volume_change_pct": 10.06,
          "ma50": 85.68,
          "ema25": 85.7,
          "bb_position": 0.0318,
          "above_ma50": false,
          "above_ema25": false,
          "flags": {
            "rsi_oversold": false,
            "rsi_overbought": false,
            "rsi_neutral": false,
            "near_upper_band": false,
            "near_lower_band": true,
            "price_above_ma50": false,
            "price_above_ema25": false,
            "volume_surge": false,
            "volume_dry": false
          }
        },
        "2d": {
          "close": 77.9,
          "rsi": 37.4,
          "volume_change_pct": -23.77,
          "ma50": 103.3,
          "ema25": 89.8,
          "bb_position": 0.0577,
          "above_ma50": false,
          "above_ema25": false,
          "flags": {
            "rsi_oversold": false,
            "rsi_overbought": false,
            "rsi_neutral": false,
            "near_upper_band": false,
            "near_lower_band": true,
            "price_above_ma50": false,
            "price_above_ema25": false,
            "volume_surge": false,
            "volume_dry": false
          }
        }
      },
      "open_interest": {
        "current_usd": 779455323.0,
        "change_pct_1h": -0.84,
        "change_pct_24h": -0.54,
        "momentum_state": "decelerating",
        "acceleration": -0.71
      },
      "cvd": {
        "futures": {
          "million": -1.12,
          "sma": -1.11,
          "above_sma": false,
          "buy_pct": 42.67,
          "sell_pct": 57.33
        },
        "spot": {
          "cvd_pct": 4.18,
          "buy_pct": 52.1,
          "sell_pct": 47.9
        },
        "divergence": 18.83,
        "divergence_confidence": "low"
      },
      "liquidation": {
        "symbol": "SOL",
        "1h_long_usd": 1664717.0,
        "1h_short_usd": 25695.0,
        "4h_long_usd": 3221335.0,
        "4h_short_usd": 102244.0,
        "12h_long_usd": 13896897.0,
        "12h_short_usd": 497259.0,
        "24h_long_usd": 21325868.0,
        "24h_short_usd": 5307057.0,
        "status": "success",
        "total_liquidation_12h": 14394156.0,
        "long_ratio": 96.55,
        "short_ratio": 3.45,
        "_liquidation_note": "12h/24h_long_usd=해당 기간 롱 포지션 강제청산 금액(USD). short_usd=숏 청산 금액. 롱 청산이 많으면 하락 중 롱이 밀린것, 숏 청산이 많으면 상승 중 숏이 밀린것. long_ratio/short_ratio=전체 청산 중 비중(%)",
        "timestamp": 1775134767,
        "source": "coinglass",
        "data_interval": "12h"
      },
      "relative_strength_vs_btc": {
        "1h": 2.48,
        "4h": 4.28,
        "1d": 1.53,
        "1w": -1.02
      },
      "whale_reference": {
        "status": "success",
        "vwap": 84.27,
        "distance_pct": -7.59,
        "usable": true,
        "cache_reason": null
      },
      "support_resistance": {
        "supports": [
          67.29,
          75.57
        ],
        "resistances": [
          83.18,
          84.38,
          85.31,
          90.21
        ]
      },
      "orderbook": {
        "buy_nearest": 78.0,
        "sell_nearest": 78.04,
        "top_buy": [
          77.94,
          77.97,
          77.91
        ],
        "top_sell": [
          78.07,
          78.08,
          78.04
        ],
        "imbalance_ratio": 1.215
      },
      "warnings": [
        "volume_contracting"
      ]
    },
    "BTCUSDT": {
      "price": 66003.1,
      "change_24h_pct": -3.44,
      "funding_rate": -4.111e-05,
      "timeframes": {
        "15m": {
          "close": 65993.8,
          "rsi": 34.0,
          "volume_change_pct": 30.49,
          "ma50": 66651.12,
          "ema25": 66389.03,
          "bb_position": 0.006,
          "above_ma50": false,
          "above_ema25": false,
          "flags": {
            "rsi_oversold": false,
            "rsi_overbought": false,
            "rsi_neutral": false,
            "near_upper_band": false,
            "near_lower_band": true,
            "price_above_ma50": false,
            "price_above_ema25": false,
            "volume_surge": false,
            "volume_dry": false
          }
        },
        "30m": {
          "close": 66000.0,
          "rsi": 27.9,
          "volume_change_pct": -9.8,
          "ma50": 67496.59,
          "ema25": 66714.02,
          "bb_position": -0.0247,
          "above_ma50": false,
          "above_ema25": false,
          "flags": {
            "rsi_oversold": true,
            "rsi_overbought": false,
            "rsi_neutral": false,
            "near_upper_band": false,
            "near_lower_band": true,
            "price_above_ma50": false,
            "price_above_ema25": false,
            "volume_surge": false,
            "volume_dry": false
          }
        },
        "1h": {
          "close": 66003.1,
          "rsi": 32.0,
          "volume_change_pct": -20.46,
          "ma50": 67697.99,
          "ema25": 67146.92,
          "bb_position": 0.1584,
          "above_ma50": false,
          "above_ema25": false,
          "flags": {
            "rsi_oversold": false,
            "rsi_overbought": false,
            "rsi_neutral": false,
            "near_upper_band": false,
            "near_lower_band": true,
            "price_above_ma50": false,
            "price_above_ema25": false,
            "volume_surge": false,
            "volume_dry": false
          }
        },
        "4h": {
          "close": 66004.2,
          "rsi": 38.6,
          "volume_change_pct": -27.56,
          "ma50": 67711.82,
          "ema25": 67382.66,
          "bb_position": 0.0859,
          "above_ma50": false,
          "above_ema25": false,
          "flags": {
            "rsi_oversold": false,
            "rsi_overbought": false,
            "rsi_neutral": false,
            "near_upper_band": false,
            "near_lower_band": true,
            "price_above_ma50": false,
            "price_above_ema25": false,
            "volume_surge": false,
            "volume_dry": false
          }
        },
        "1d": {
          "close": 65996.9,
          "rsi": 41.5,
          "volume_change_pct": -9.37,
          "ma50": 68627.04,
          "ema25": 68781.1,
          "bb_position": 0.1651,
          "above_ma50": false,
          "above_ema25": false,
          "flags": {
            "rsi_oversold": false,
            "rsi_overbought": false,
            "rsi_neutral": true,
            "near_upper_band": false,
            "near_lower_band": true,
            "price_above_ma50": false,
            "price_above_ema25": false,
            "volume_surge": false,
            "volume_dry": false
          }
        },
        "2d": {
          "close": 66000.0,
          "rsi": 41.0,
          "volume_change_pct": -22.9,
          "ma50": 76975.14,
          "ema25": 70586.81,
          "bb_position": 0.2357,
          "above_ma50": false,
          "above_ema25": false,
          "flags": {
            "rsi_oversold": false,
            "rsi_overbought": false,
            "rsi_neutral": true,
            "near_upper_band": false,
            "near_lower_band": false,
            "price_above_ma50": false,
            "price_above_ema25": false,
            "volume_surge": false,
            "volume_dry": false
          }
        }
      },
      "open_interest": {
        "current_usd": 5872066344.0,
        "change_pct_1h": -0.37,
        "change_pct_24h": -5.49,
        "momentum_state": "decelerating",
        "acceleration": -0.59
      },
      "cvd": {
        "futures": {
          "million": -1.52,
          "sma": 0.13,
          "above_sma": false,
          "buy_pct": 42.2,
          "sell_pct": 57.8
        },
        "spot": {
          "cvd_pct": 1.32,
          "buy_pct": 50.7,
          "sell_pct": 49.3
        },
        "divergence": 16.92,
        "divergence_confidence": "low"
      },
      "liquidation": {
        "symbol": "BTC",
        "1h_long_usd": 4330148.0,
        "1h_short_usd": 87359.0,
        "4h_long_usd": 8808263.0,
        "4h_short_usd": 478549.0,
        "12h_long_usd": 58338125.0,
        "12h_short_usd": 3243651.0,
        "24h_long_usd": 68891352.0,
        "24h_short_usd": 15793357.0,
        "status": "success",
        "total_liquidation_12h": 61581776.0,
        "long_ratio": 94.73,
        "short_ratio": 5.27,
        "_liquidation_note": "12h/24h_long_usd=해당 기간 롱 포지션 강제청산 금액(USD). short_usd=숏 청산 금액. 롱 청산이 많으면 하락 중 롱이 밀린것, 숏 청산이 많으면 상승 중 숏이 밀린것. long_ratio/short_ratio=전체 청산 중 비중(%)",
        "timestamp": 1775134743,
        "source": "coinglass",
        "data_interval": "12h"
      },
      "relative_strength_vs_btc": null,
      "whale_reference": {
        "status": "stale_cached",
        "vwap": 68009.7,
        "distance_pct": -2.34,
        "usable": false,
        "cache_reason": "no_oi_spike"
      },
      "support_resistance": {
        "supports": [
          48888.0,
          55846.84,
          59800.0,
          65616.94
        ],
        "resistances": [
          67122.87,
          68327.04,
          69277.61,
          70732.96
        ]
      },
      "orderbook": {
        "buy_nearest": 66050.98,
        "sell_nearest": 66115.57,
        "top_buy": [],
        "top_sell": [],
        "imbalance_ratio": 0.782
      },
      "warnings": []
    }
  }
}