{
  "timestamp": "2026-04-02T13:05:18.147466",
  "generated_at_local": "2026-04-02 13:05:18 KST",
  "candle_close_time": "2026-04-02 13:00 KST",
  "exchange": "binance",
  "market_type": "futures",
  "timezone": "Asia/Seoul",
  "symbol_primary": "SOLUSDT",
  "symbol_reference": "BTCUSDT",
  "_format": "compact",
  "_note": "15분봉 완성 시점 자동 생성. candle_close_time이 데이터 기준 시점.",
  "assets": {
    "SOLUSDT": {
      "price": 79.01,
      "change_24h_pct": -5.33,
      "funding_rate": -0.0001924,
      "timeframes": {
        "15m": {
          "close": 79.02,
          "rsi": 34.6,
          "volume_change_pct": -23.4,
          "ma50": 81.91,
          "ema25": 80.07,
          "bb_position": 0.3246,
          "above_ma50": false,
          "above_ema25": false,
          "flags": {
            "rsi_oversold": false,
            "rsi_overbought": false,
            "rsi_neutral": false,
            "near_upper_band": false,
            "near_lower_band": false,
            "price_above_ma50": false,
            "price_above_ema25": false,
            "volume_surge": false,
            "volume_dry": false
          }
        },
        "30m": {
          "close": 79.01,
          "rsi": 30.9,
          "volume_change_pct": 28.49,
          "ma50": 82.65,
          "ema25": 81.05,
          "bb_position": 0.2071,
          "above_ma50": false,
          "above_ema25": false,
          "flags": {
            "rsi_oversold": false,
            "rsi_overbought": false,
            "rsi_neutral": false,
            "near_upper_band": false,
            "near_lower_band": false,
            "price_above_ma50": false,
            "price_above_ema25": false,
            "volume_surge": false,
            "volume_dry": false
          }
        },
        "1h": {
          "close": 79.01,
          "rsi": 30.4,
          "volume_change_pct": 5.96,
          "ma50": 82.44,
          "ema25": 81.77,
          "bb_position": 0.0859,
          "above_ma50": false,
          "above_ema25": false,
          "flags": {
            "rsi_oversold": false,
            "rsi_overbought": false,
            "rsi_neutral": false,
            "near_upper_band": false,
            "near_lower_band": true,
            "price_above_ma50": false,
            "price_above_ema25": false,
            "volume_surge": false,
            "volume_dry": false
          }
        },
        "4h": {
          "close": 79.01,
          "rsi": 33.6,
          "volume_change_pct": -1.8,
          "ma50": 84.5,
          "ema25": 82.6,
          "bb_position": -0.0529,
          "above_ma50": false,
          "above_ema25": false,
          "flags": {
            "rsi_oversold": false,
            "rsi_overbought": false,
            "rsi_neutral": false,
            "near_upper_band": false,
            "near_lower_band": true,
            "price_above_ma50": false,
            "price_above_ema25": false,
            "volume_surge": false,
            "volume_dry": false
          }
        },
        "1d": {
          "close": 79.01,
          "rsi": 37.1,
          "volume_change_pct": 6.13,
          "ma50": 85.71,
          "ema25": 85.78,
          "bb_position": 0.0751,
          "above_ma50": false,
          "above_ema25": false,
          "flags": {
            "rsi_oversold": false,
            "rsi_overbought": false,
            "rsi_neutral": false,
            "near_upper_band": false,
            "near_lower_band": true,
            "price_above_ma50": false,
            "price_above_ema25": false,
            "volume_surge": false,
            "volume_dry": false
          }
        },
        "2d": {
          "close": 79.02,
          "rsi": 38.2,
          "volume_change_pct": -25.19,
          "ma50": 103.32,
          "ema25": 89.88,
          "bb_position": 0.107,
          "above_ma50": false,
          "above_ema25": false,
          "flags": {
            "rsi_oversold": false,
            "rsi_overbought": false,
            "rsi_neutral": false,
            "near_upper_band": false,
            "near_lower_band": true,
            "price_above_ma50": false,
            "price_above_ema25": false,
            "volume_surge": false,
            "volume_dry": false
          }
        }
      },
      "open_interest": {
        "current_usd": 772078359.0,
        "change_pct_1h": 1.65,
        "change_pct_24h": -2.89,
        "momentum_state": "accelerating",
        "acceleration": 1.77
      },
      "cvd": {
        "futures": {
          "million": 0.67,
          "sma": -0.55,
          "above_sma": true,
          "buy_pct": 54.57,
          "sell_pct": 45.43
        },
        "spot": {
          "cvd_pct": 2.03,
          "buy_pct": 51.0,
          "sell_pct": 49.0
        },
        "divergence": -7.12,
        "divergence_confidence": "low"
      },
      "liquidation": {
        "symbol": "SOL",
        "1h_long_usd": 184577.0,
        "1h_short_usd": 52460.0,
        "4h_long_usd": 9964342.0,
        "4h_short_usd": 459629.0,
        "12h_long_usd": 16649173.0,
        "12h_short_usd": 4803707.0,
        "24h_long_usd": 18024713.0,
        "24h_short_usd": 6768487.0,
        "status": "success",
        "total_liquidation_12h": 21452880.0,
        "long_ratio": 77.61,
        "short_ratio": 22.39,
        "_liquidation_note": "12h/24h_long_usd=해당 기간 롱 포지션 강제청산 금액(USD). short_usd=숏 청산 금액. 롱 청산이 많으면 하락 중 롱이 밀린것, 숏 청산이 많으면 상승 중 숏이 밀린것. long_ratio/short_ratio=전체 청산 중 비중(%)",
        "timestamp": 1775102616,
        "source": "coinglass",
        "data_interval": "12h"
      },
      "relative_strength_vs_btc": {
        "1h": 2.18,
        "4h": 4.25,
        "1d": 1.54,
        "1w": -0.97
      },
      "whale_reference": {
        "status": "success",
        "vwap": 82.83,
        "distance_pct": -4.59,
        "usable": true,
        "cache_reason": null
      },
      "support_resistance": {
        "supports": [
          67.29,
          75.57,
          78.75
        ],
        "resistances": [
          82.22,
          83.53,
          84.93,
          90.29
        ]
      },
      "orderbook": {
        "buy_nearest": 79.02,
        "sell_nearest": 79.07,
        "top_buy": [
          78.97,
          78.99,
          78.96
        ],
        "top_sell": [
          79.1,
          79.15,
          79.07
        ],
        "imbalance_ratio": 1.482
      },
      "warnings": []
    },
    "BTCUSDT": {
      "price": 66594.5,
      "change_24h_pct": -2.32,
      "funding_rate": -3.147e-05,
      "timeframes": {
        "15m": {
          "close": 66594.5,
          "rsi": 30.4,
          "volume_change_pct": -33.88,
          "ma50": 67949.41,
          "ema25": 67354.14,
          "bb_position": 0.2202,
          "above_ma50": false,
          "above_ema25": false,
          "flags": {
            "rsi_oversold": false,
            "rsi_overbought": false,
            "rsi_neutral": false,
            "near_upper_band": false,
            "near_lower_band": false,
            "price_above_ma50": false,
            "price_above_ema25": false,
            "volume_surge": false,
            "volume_dry": true
          }
        },
        "30m": {
          "close": 66594.5,
          "rsi": 27.8,
          "volume_change_pct": 219.81,
          "ma50": 68222.62,
          "ema25": 67687.75,
          "bb_position": 0.0644,
          "above_ma50": false,
          "above_ema25": false,
          "flags": {
            "rsi_oversold": true,
            "rsi_overbought": false,
            "rsi_neutral": false,
            "near_upper_band": false,
            "near_lower_band": true,
            "price_above_ma50": false,
            "price_above_ema25": false,
            "volume_surge": true,
            "volume_dry": false
          }
        },
        "1h": {
          "close": 66594.5,
          "rsi": 33.9,
          "volume_change_pct": -10.19,
          "ma50": 67809.06,
          "ema25": 67835.19,
          "bb_position": -0.026,
          "above_ma50": false,
          "above_ema25": false,
          "flags": {
            "rsi_oversold": false,
            "rsi_overbought": false,
            "rsi_neutral": false,
            "near_upper_band": false,
            "near_lower_band": true,
            "price_above_ma50": false,
            "price_above_ema25": false,
            "volume_surge": false,
            "volume_dry": false
          }
        },
        "4h": {
          "close": 66603.0,
          "rsi": 41.7,
          "volume_change_pct": -19.44,
          "ma50": 67894.21,
          "ema25": 67585.36,
          "bb_position": 0.1844,
          "above_ma50": false,
          "above_ema25": false,
          "flags": {
            "rsi_oversold": false,
            "rsi_overbought": false,
            "rsi_neutral": true,
            "near_upper_band": false,
            "near_lower_band": true,
            "price_above_ma50": false,
            "price_above_ema25": false,
            "volume_surge": false,
            "volume_dry": false
          }
        },
        "1d": {
          "close": 66594.5,
          "rsi": 42.9,
          "volume_change_pct": -12.31,
          "ma50": 68638.99,
          "ema25": 68827.07,
          "bb_position": 0.215,
          "above_ma50": false,
          "above_ema25": false,
          "flags": {
            "rsi_oversold": false,
            "rsi_overbought": false,
            "rsi_neutral": true,
            "near_upper_band": false,
            "near_lower_band": false,
            "price_above_ma50": false,
            "price_above_ema25": false,
            "volume_surge": false,
            "volume_dry": false
          }
        },
        "2d": {
          "close": 66594.5,
          "rsi": 41.8,
          "volume_change_pct": -24.09,
          "ma50": 76987.03,
          "ema25": 70632.54,
          "bb_position": 0.2884,
          "above_ma50": false,
          "above_ema25": false,
          "flags": {
            "rsi_oversold": false,
            "rsi_overbought": false,
            "rsi_neutral": true,
            "near_upper_band": false,
            "near_lower_band": false,
            "price_above_ma50": false,
            "price_above_ema25": false,
            "volume_surge": false,
            "volume_dry": false
          }
        }
      },
      "open_interest": {
        "current_usd": 5889389235.0,
        "change_pct_1h": -0.22,
        "change_pct_24h": -4.75,
        "momentum_state": "accelerating",
        "acceleration": 0.6
      },
      "cvd": {
        "futures": {
          "million": 1.08,
          "sma": -0.17,
          "above_sma": true,
          "buy_pct": 58.79,
          "sell_pct": 41.21
        },
        "spot": {
          "cvd_pct": 3.9,
          "buy_pct": 52.0,
          "sell_pct": 48.0
        },
        "divergence": -13.67,
        "divergence_confidence": "low"
      },
      "liquidation": {
        "symbol": "BTC",
        "1h_long_usd": 3637761.0,
        "1h_short_usd": 54104.0,
        "4h_long_usd": 41713195.0,
        "4h_short_usd": 2390247.0,
        "12h_long_usd": 48616621.0,
        "12h_short_usd": 9604988.0,
        "24h_long_usd": 57378021.0,
        "24h_short_usd": 40971424.0,
        "status": "success",
        "total_liquidation_12h": 58221609.0,
        "long_ratio": 83.5,
        "short_ratio": 16.5,
        "_liquidation_note": "12h/24h_long_usd=해당 기간 롱 포지션 강제청산 금액(USD). short_usd=숏 청산 금액. 롱 청산이 많으면 하락 중 롱이 밀린것, 숏 청산이 많으면 상승 중 숏이 밀린것. long_ratio/short_ratio=전체 청산 중 비중(%)",
        "timestamp": 1775102592,
        "source": "coinglass",
        "data_interval": "12h"
      },
      "relative_strength_vs_btc": null,
      "whale_reference": {
        "status": "success",
        "vwap": 68009.7,
        "distance_pct": -2.07,
        "usable": true,
        "cache_reason": null
      },
      "support_resistance": {
        "supports": [
          59800.0,
          62401.7,
          65592.61,
          66528.48
        ],
        "resistances": [
          67081.64,
          68262.99,
          69331.04,
          70732.96
        ]
      },
      "orderbook": {
        "buy_nearest": 66526.68,
        "sell_nearest": 66589.81,
        "top_buy": [
          66500.0
        ],
        "top_sell": [
          66604.7
        ],
        "imbalance_ratio": 0.919
      },
      "warnings": []
    }
  }
}